{
  "subjects": [
    {
      "id": "54qlawvp",
      "name": "QUANTS",
      "color": "#dc2626"
    },
    {
      "id": "qizeq571",
      "name": "VARC",
      "color": "#ea580c"
    },
    {
      "id": "pvjevrgq",
      "name": "LRDI",
      "color": "#7c3aed"
    },
    {
      "id": "6ruqhcbn",
      "name": "VARC1000 BY GEJO",
      "color": "#7c3aed"
    }
  ],
  "topics": [
    {
      "id": "oo1f3pn6",
      "subjectId": "54qlawvp",
      "name": "RATIO & PROPORTION + MF",
      "difficulty": "Easy",
      "totalClasses": 8,
      "doneClasses": 8,
      "totalTests": 19,
      "doneTests": 0,
      "totalPYQ": 0,
      "donePYQ": 0,
      "totalQuestions": 0,
      "doneQuestions": 0,
      "notes": "",
      "theoryComplete": false
    },
    {
      "id": "7wvly0ha",
      "subjectId": "54qlawvp",
      "name": "PERCENTAGES",
      "difficulty": "Easy",
      "totalClasses": 6,
      "doneClasses": 6,
      "totalTests": 20,
      "doneTests": 0,
      "totalPYQ": 0,
      "donePYQ": 0,
      "totalQuestions": 0,
      "doneQuestions": 0,
      "notes": "",
      "theoryComplete": false
    },
    {
      "id": "6b8ih9z3",
      "subjectId": "54qlawvp",
      "name": "TIME & WORK",
      "difficulty": "Medium",
      "totalClasses": 4,
      "doneClasses": 1,
      "totalTests": 11,
      "doneTests": 0,
      "totalPYQ": 0,
      "donePYQ": 0,
      "totalQuestions": 0,
      "doneQuestions": 0,
      "notes": "",
      "theoryComplete": false
    },
    {
      "id": "nf9qjs9f",
      "subjectId": "54qlawvp",
      "name": "PROFIT & LOSS",
      "difficulty": "Medium",
      "totalClasses": 4,
      "doneClasses": 4,
      "totalTests": 19,
      "doneTests": 0,
      "totalPYQ": 0,
      "donePYQ": 0,
      "totalQuestions": 0,
      "doneQuestions": 0,
      "notes": "",
      "theoryComplete": false
    },
    {
      "id": "ma9iwxs0",
      "subjectId": "54qlawvp",
      "name": "SI-CI & PARTNERSHIP",
      "difficulty": "Medium",
      "totalClasses": 5,
      "doneClasses": 0,
      "totalTests": 0,
      "doneTests": 0,
      "totalPYQ": 0,
      "donePYQ": 0,
      "totalQuestions": 0,
      "doneQuestions": 0,
      "notes": "",
      "theoryComplete": false
    },
    {
      "id": "11lwgzkz",
      "subjectId": "pvjevrgq",
      "name": "MIXED ARRANGEMENTS",
      "difficulty": "Medium",
      "totalClasses": 11,
      "doneClasses": 0,
      "totalTests": 45,
      "doneTests": 0,
      "totalPYQ": 0,
      "donePYQ": 0,
      "totalQuestions": 0,
      "doneQuestions": 0,
      "notes": "",
      "theoryComplete": false
    },
    {
      "id": "6u7z4qui",
      "subjectId": "pvjevrgq",
      "name": "PROJECT MANAGEMENT",
      "difficulty": "Medium",
      "totalClasses": 1,
      "doneClasses": 0,
      "totalTests": 0,
      "doneTests": 0,
      "totalPYQ": 0,
      "donePYQ": 0,
      "totalQuestions": 0,
      "doneQuestions": 0,
      "notes": "",
      "theoryComplete": false
    },
    {
      "id": "lyebtyl8",
      "subjectId": "pvjevrgq",
      "name": "ADVANCED LRDI PUZZLES",
      "difficulty": "Medium",
      "totalClasses": 2,
      "doneClasses": 0,
      "totalTests": 14,
      "doneTests": 0,
      "totalPYQ": 0,
      "donePYQ": 0,
      "totalQuestions": 0,
      "doneQuestions": 0,
      "notes": "",
      "theoryComplete": false
    },
    {
      "id": "g96t6izj",
      "subjectId": "pvjevrgq",
      "name": "GAMES",
      "difficulty": "Medium",
      "totalClasses": 4,
      "doneClasses": 0,
      "totalTests": 0,
      "doneTests": 0,
      "totalPYQ": 0,
      "donePYQ": 0,
      "totalQuestions": 0,
      "doneQuestions": 0,
      "notes": "",
      "theoryComplete": false
    },
    {
      "id": "7jfja1wh",
      "subjectId": "pvjevrgq",
      "name": "ROUTES AND NETWORK",
      "difficulty": "Medium",
      "totalClasses": 3,
      "doneClasses": 0,
      "totalTests": 0,
      "doneTests": 0,
      "totalPYQ": 0,
      "donePYQ": 0,
      "totalQuestions": 0,
      "doneQuestions": 0,
      "notes": "",
      "theoryComplete": false
    },
    {
      "id": "1ixfhybf",
      "subjectId": "pvjevrgq",
      "name": "DI-CHARTS",
      "difficulty": "Medium",
      "totalClasses": 3,
      "doneClasses": 0,
      "totalTests": 0,
      "doneTests": 0,
      "totalPYQ": 0,
      "donePYQ": 0,
      "totalQuestions": 0,
      "doneQuestions": 0,
      "notes": "",
      "theoryComplete": false
    },
    {
      "id": "w64ikrrp",
      "subjectId": "pvjevrgq",
      "name": "LRDI PYQS",
      "difficulty": "Medium",
      "totalClasses": 0,
      "doneClasses": 0,
      "totalTests": 4,
      "doneTests": 0,
      "totalPYQ": 0,
      "donePYQ": 0,
      "totalQuestions": 0,
      "doneQuestions": 0,
      "notes": "",
      "theoryComplete": false
    },
    {
      "id": "btap5wu3",
      "subjectId": "pvjevrgq",
      "name": "CAT ORIENTED LRDI PUZZLES (PDF)",
      "difficulty": "Medium",
      "totalClasses": 0,
      "doneClasses": 0,
      "totalTests": 29,
      "doneTests": 0,
      "totalPYQ": 0,
      "donePYQ": 0,
      "totalQuestions": 0,
      "doneQuestions": 0,
      "notes": "",
      "theoryComplete": false
    },
    {
      "id": "9va5e96n",
      "subjectId": "6ruqhcbn",
      "name": "Getting Started",
      "difficulty": "Easy",
      "totalClasses": 3,
      "doneClasses": 3,
      "totalTests": 1,
      "doneTests": 1,
      "totalPYQ": 0,
      "donePYQ": 0,
      "totalQuestions": 0,
      "doneQuestions": 0,
      "notes": "",
      "theoryComplete": true
    },
    {
      "id": "q2omul1y",
      "subjectId": "6ruqhcbn",
      "name": "Module 1",
      "difficulty": "Medium",
      "totalClasses": 5,
      "doneClasses": 0,
      "totalTests": 5,
      "doneTests": 0,
      "totalPYQ": 0,
      "donePYQ": 0,
      "totalQuestions": 0,
      "doneQuestions": 0,
      "notes": "",
      "theoryComplete": false
    },
    {
      "id": "z8714yg6",
      "subjectId": "6ruqhcbn",
      "name": "Article Dose",
      "difficulty": "Medium",
      "totalClasses": 0,
      "doneClasses": 0,
      "totalTests": 25,
      "doneTests": 0,
      "totalPYQ": 0,
      "donePYQ": 0,
      "totalQuestions": 0,
      "doneQuestions": 0,
      "notes": "",
      "theoryComplete": false
    },
    {
      "id": "wyhx6ywv",
      "subjectId": "54qlawvp",
      "name": "Average Allegation Mixture",
      "difficulty": "Medium",
      "totalClasses": 3,
      "doneClasses": 0,
      "totalTests": 0,
      "doneTests": 0,
      "totalPYQ": 0,
      "donePYQ": 0,
      "totalQuestions": 0,
      "doneQuestions": 0,
      "notes": "",
      "theoryComplete": false
    },
    {
      "id": "5yvuukld",
      "subjectId": "54qlawvp",
      "name": "Set Theory",
      "difficulty": "Medium",
      "totalClasses": 2,
      "doneClasses": 1,
      "totalTests": 0,
      "doneTests": 0,
      "totalPYQ": 0,
      "donePYQ": 0,
      "totalQuestions": 0,
      "doneQuestions": 0,
      "notes": "",
      "theoryComplete": false
    }
  ],
  "tasks": {},
  "mocks": [
    {
      "id": "q6asm93g",
      "name": "CL FLEXI 1",
      "date": "2026-04-07",
      "provider": "CL",
      "type": "Full Mock",
      "notes": "VARC- 82.5\nLRDI- 80.4\nQUANT - 6.9",
      "attempted": true,
      "analysed": false,
      "score": {
        "varc": 22,
        "lrdi": 11,
        "quant": -2,
        "total": 31,
        "percentile": 59.97,
        "rank": null
      }
    }
  ],
  "revisions": [],
  "settings": {
    "theme": "light"
  }
}